{
  "displayWeekday": "Sunday",
  "displayDate": "June 4, 2023",
  "printDate": "2023-06-04",
  "centerLetter": "b",
  "outerLetters": [
    "a",
    "d",
    "i",
    "m",
    "n",
    "r"
  ],
  "validLetters": [
    "b",
    "a",
    "d",
    "i",
    "m",
    "n",
    "r"
  ],
  "pangrams": [
    "midbrain"
  ],
  "answers": [
    "midbrain",
    "armband",
    "baba",
    "banana",
    "band",
    "bandana",
    "bandanna",
    "barb",
    "barbarian",
    "bard",
    "barmaid",
    "barman",
    "barn",
    "bind",
    "bindi",
    "bird",
    "birdbrain",
    "brad",
    "braid",
    "brain",
    "bran",
    "brand",
    "briar",
    "brim",
    "drab",
    "drib",
    "iamb",
    "iambi",
    "mamba",
    "marimba",
    "midrib",
    "minibar",
    "nimbi",
    "rabbi",
    "rabid"
  ],
  "id": 16486,
  "freeExpiration": 0,
  "editor": "Sam Ezersky"
}
