{
  "expiration": 1695884400,
  "displayWeekday": "Wednesday",
  "displayDate": "September 27, 2023",
  "printDate": "2023-09-27",
  "centerLetter": "l",
  "outerLetters": [
    "c",
    "e",
    "f",
    "n",
    "o",
    "u"
  ],
  "validLetters": [
    "l",
    "c",
    "e",
    "f",
    "n",
    "o",
    "u"
  ],
  "pangrams": [
    "confluence",
    "flounce"
  ],
  "answers": [
    "confluence",
    "flounce",
    "cell",
    "cello",
    "cellule",
    "clef",
    "clone",
    "clue",
    "colleen",
    "colon",
    "colonel",
    "cool",
    "coulee",
    "cull",
    "effluence",
    "feel",
    "fell",
    "felon",
    "fennel",
    "flee",
    "fleece",
    "floe",
    "flue",
    "fluff",
    "fool",
    "foul",
    "fuel",
    "full",
    "funnel",
    "loco",
    "loll",
    "lone",
    "loon",
    "lull",
    "lulu",
    "lune",
    "noel",
    "nucleon",
    "null",
    "oleo",
    "uncle",
    "uncool"
  ],
  "id": 19142,
  "freeExpiration": 0,
  "editor": "Sam Ezersky"
}
