{
  "displayWeekday": "Sunday",
  "displayDate": "August 4, 2024",
  "printDate": "2024-08-04",
  "centerLetter": "t",
  "outerLetters": [
    "b",
    "h",
    "i",
    "n",
    "o",
    "r"
  ],
  "validLetters": [
    "t",
    "b",
    "h",
    "i",
    "n",
    "o",
    "r"
  ],
  "pangrams": [
    "inhibitor"
  ],
  "answers": [
    "inhibitor",
    "biotin",
    "birth",
    "bonito",
    "boot",
    "booth",
    "both",
    "broth",
    "hint",
    "hobbit",
    "hoot",
    "inhibit",
    "inhibition",
    "into",
    "intro",
    "ninth",
    "nitro",
    "north",
    "notion",
    "obit",
    "onto",
    "orbit",
    "ribbit",
    "riot",
    "robot",
    "root",
    "roti",
    "rotini",
    "rotor",
    "thin",
    "thorn",
    "throb",
    "tinhorn",
    "tint",
    "toon",
    "toot",
    "tooth",
    "tori",
    "torii",
    "torn",
    "toro",
    "tort",
    "tortoni",
    "trio",
    "triton",
    "trot",
    "troth"
  ],
  "id": 19027,
  "freeExpiration": 0,
  "editor": "Sam Ezersky"
}
