{
  "displayWeekday": "Thursday",
  "displayDate": "June 27, 2024",
  "printDate": "2024-06-27",
  "centerLetter": "o",
  "outerLetters": [
    "a",
    "k",
    "m",
    "n",
    "r",
    "w"
  ],
  "validLetters": [
    "o",
    "a",
    "k",
    "m",
    "n",
    "r",
    "w"
  ],
  "pangrams": [
    "workman",
    "workwoman"
  ],
  "answers": [
    "workman",
    "workwoman",
    "ammo",
    "amok",
    "anon",
    "anorak",
    "armor",
    "aroma",
    "arrow",
    "know",
    "known",
    "koan",
    "kook",
    "korma",
    "krona",
    "kronor",
    "kroon",
    "mako",
    "mammon",
    "manor",
    "maroon",
    "marrow",
    "moan",
    "momma",
    "monk",
    "mono",
    "moon",
    "moor",
    "morn",
    "moron",
    "morrow",
    "mown",
    "narrow",
    "nook",
    "noon",
    "norm",
    "okra",
    "roam",
    "roan",
    "roar",
    "rook",
    "room",
    "rowan",
    "woman",
    "wonk",
    "work",
    "workroom",
    "worm",
    "worn"
  ],
  "id": 19909,
  "freeExpiration": 0,
  "editor": "Sam Ezersky"
}
