{
  "displayWeekday": "Monday",
  "displayDate": "March 25, 2024",
  "printDate": "2024-03-25",
  "centerLetter": "b",
  "outerLetters": [
    "g",
    "i",
    "l",
    "m",
    "n",
    "o"
  ],
  "validLetters": [
    "b",
    "g",
    "i",
    "l",
    "m",
    "n",
    "o"
  ],
  "pangrams": [
    "blooming"
  ],
  "answers": [
    "blooming",
    "bill",
    "billing",
    "billion",
    "binging",
    "bingo",
    "binning",
    "blin",
    "bling",
    "blini",
    "blob",
    "blobbing",
    "blog",
    "blogging",
    "bloom",
    "bobbin",
    "bobbing",
    "bobbling",
    "bogging",
    "boggling",
    "boil",
    "boiling",
    "boing",
    "boll",
    "bolo",
    "bomb",
    "bombing",
    "bonbon",
    "bong",
    "bongo",
    "boning",
    "bonobo",
    "boob",
    "booboo",
    "booing",
    "boom",
    "booming",
    "boon",
    "gibbon",
    "gibing",
    "glib",
    "glob",
    "gobbling",
    "goblin",
    "imbibing",
    "limb",
    "limbo",
    "lobbing",
    "lobo",
    "mobbing",
    "nibbling",
    "nimbi",
    "noob",
    "obliging",
    "oblong"
  ],
  "id": 20715,
  "freeExpiration": 0,
  "editor": "Sam Ezersky"
}
